Workbook

Sheet README
A1: ATLAS Monthly Portfolio Upload Template
A2: One standardized file to refresh the full monthly ATLAS dashboard across all communities.
A4: Workflow Step | B4: Action | D4: Recommended Tagline
A5: 1 | B5: Update Community_Master only when a community or mapping changes. | D5: LOVE. SERVE. CARE.
A6: 2 | B6: Paste one row per community per month into Monthly_Upload. | D6: Powered by better insight, stronger service, and care for every community.
A7: 3 | B7: Use dropdowns and Row_Status / Error_Detail to correct issues.
A8: 4 | B8: Review Upload_Checks before loading. | D8: Primary Keys | E8: Report_Month + Community_ID
A9: 5 | B9: Load Monthly_Upload into Power BI / ATLAS as the monthly fact table. | D9: Community Mapping | E9: Community_ID joins every upload row to dashboard visuals.
A10: 6 | B10: Save as ATLAS_MonthlyUpload_YYYY-MM.xlsx. | D10: Power BI Grain | E10: One row per community per reporting month.
D11: Do Not Rename | E11: Monthly_Upload, Community_Master, Data_Dictionary, Upload_Checks
D12: Agent Role | E12: Clean, map, validate, and return exactly this schema.

Sheet Monthly_Upload
A1: Report_Month | B1: Community_ID | C1: Community_Name | D1: Region | E1: Market | F1: Asset_Type | G1: PMS_Property_Code | H1: Total_Units | I1: Occupied_Units | J1: Leased_Units | K1: Preleased_Units | L1: Vacant_Units | M1: Physical_Occupancy_% | N1: Leased_% | O1: Economic_Occupancy_% | P1: Avg_Market_Rent | Q1: Actual_Rent | R1: Concessions_$ | S1: Delinquency_$ | T1: Gross_Potential_Rent_$ | U1: Collected_Rent_$ | V1: Other_Income_$ | W1: Operating_Expenses_$ | X1: NOI_$ | Y1: Traffic | Z1: Leads | AA1: Tours | AB1: Applications | AC1: Approved_Applications | AD1: Move_Ins | AE1: Move_Outs | AF1: Renewals_Sent | AG1: Renewals_Signed | AH1: Reviews_Count | AI1: Avg_Review_Rating | AJ1: Open_Work_Orders | AK1: Completed_Work_Orders | AL1: Period_Status | AM1: Source_System | AN1: Source_File_Name | AO1: Agent_Notes | AP1: Last_Updated | AQ1: Row_Status | AR1: Error_Detail | AS1: Lead_Walk_Ins | AT1: Lead_Calls | AU1: Lead_Emails_Online | AV1: Lead_Chat_Text_Other | AW1: Off_Site_Event | AX1: Applications_Cancelled | AY1: Exposure_%
A2: 2026-05-01 | B2: STA | C2: =IFERROR(VLOOKUP($B2,Community_Master!$A$2:$K$100,2,FALSE),"") | D2: =IFERROR(VLOOKUP($B2,Community_Master!$A$2:$K$100,4,FALSE),"") | E2: =IFERROR(VLOOKUP($B2,Community_Master!$A$2:$K$100,5,FALSE),"") | F2: =IFERROR(VLOOKUP($B2,Community_Master!$A$2:$K$100,6,FALSE),"") | G2: =IFERROR(VLOOKUP($B2,Community_Master!$A$2:$K$100,8,FALSE),"") | H2: 272 | I2: 2 | J2: 6 | K2: 4 | L2: =IF($H2="","",MAX($H2-$I2,0)) | M2: =IF($H2="","",IFERROR($I2/$H2,"")) | N2: =IF($H2="","",IFERROR($J2/$H2,"")) | P2: 2856.4 | Q2: 2500 | T2: =IF($H2="","",IFERROR($H2*$P2,"")) | X2: =IF(OR($U2="",$W2=""),"",($U2+$V2)-$W2) | Y2: 12 | Z2: 12 | AA2: 4 | AB2: 3 | AC2: 3 | AD2: 0 | AE2: 0 | AL2: Actual | AM2: Manual Upload | AN2: St_Augustine_RISE_CSV_Bundle_2026-05 | AO2: Corrected by Codex: St Augustine mapped to STA; lead source breakout and 1 cancelled application added for dashboard import. | AP2: 46153.438 | AQ2: =IF($B2="","",IF(OR(ISERROR(MATCH($B2,Community_Master!$A$2:$A$100,0)),$A2="",AND($H2<>"",$I2>$H2),AND($H2<>"",$J2>$H2),$I2<0,$J2<0,$K2<0,$P2<0,$Q2<0,$Y2<0,$Z2<0,$AA2<0,$AB2<0,$AC2<0),"ERROR","OK")) | AR2: =IF($B2="","",TRIM(IF(ISERROR(MATCH($B2,Community_Master!$A$2:$A$100,0)),"Invalid Community_ID; ","")&IF($A2="","Missing Report_Month; ","")&IF(AND($H2<>"",$I2>$H2),"Occupied_Units greater than Total_Units; ","")&IF(AND($H2<>"",$J2>$H2),"Leased_Units greater than Total_Units; ","")&IF($I2<0,"Occupied_Units negative; ","")&IF($J2<0,"Leased_Units negative; ","")&IF($P2<0,"Avg_Market_Rent negative; ",""))) | AS2: 0 | AT2: 7 | AU2: 5 | AV2: 0 | AW2: 0 | AX2: 1 | AY2: 0.0221
C3: =IFERROR(VLOOKUP($B3,Community_Master!$A$2:$K$100,2,FALSE),"") | D3: =IFERROR(VLOOKUP($B3,Community_Master!$A$2:$K$100,4,FALSE),"") | E3: =IFERROR(VLOOKUP($B3,Community_Master!$A$2:$K$100,5,FALSE),"") | F3: =IFERROR(VLOOKUP($B3,Community_Master!$A$2:$K$100,6,FALSE),"") | G3: =IFERROR(VLOOKUP($B3,Community_Master!$A$2:$K$100,8,FALSE),"") | L3: =IF($H3="","",MAX($H3-$I3,0)) | M3: =IF($H3="","",IFERROR($I3/$H3,"")) | N3: =IF($H3="","",IFERROR($J3/$H3,"")) | T3: =IF($H3="","",IFERROR($H3*$P3,"")) | X3: =IF(OR($U3="",$W3=""),"",($U3+$V3)-$W3) | AQ3: =IF($B3="","",IF(OR(ISERROR(MATCH($B3,Community_Master!$A$2:$A$100,0)),$A3="",AND($H3<>"",$I3>$H3),AND($H3<>"",$J3>$H3),$I3<0,$J3<0,$K3<0,$P3<0,$Q3<0,$Y3<0,$Z3<0,$AA3<0,$AB3<0,$AC3<0),"ERROR","OK")) | AR3: =IF($B3="","",TRIM(IF(ISERROR(MATCH($B3,Community_Master!$A$2:$A$100,0)),"Invalid Community_ID; ","")&IF($A3="","Missing Report_Month; ","")&IF(AND($H3<>"",$I3>$H3),"Occupied_Units greater than Total_Units; ","")&IF(AND($H3<>"",$J3>$H3),"Leased_Units greater than Total_Units; ","")&IF($I3<0,"Occupied_Units negative; ","")&IF($J3<0,"Leased_Units negative; ","")&IF($P3<0,"Avg_Market_Rent negative; ","")))
C4: =IFERROR(VLOOKUP($B4,Community_Master!$A$2:$K$100,2,FALSE),"") | D4: =IFERROR(VLOOKUP($B4,Community_Master!$A$2:$K$100,4,FALSE),"") | E4: =IFERROR(VLOOKUP($B4,Community_Master!$A$2:$K$100,5,FALSE),"") | F4: =IFERROR(VLOOKUP($B4,Community_Master!$A$2:$K$100,6,FALSE),"") | G4: =IFERROR(VLOOKUP($B4,Community_Master!$A$2:$K$100,8,FALSE),"") | L4: =IF($H4="","",MAX($H4-$I4,0)) | M4: =IF($H4="","",IFERROR($I4/$H4,"")) | N4: =IF($H4="","",IFERROR($J4/$H4,"")) | T4: =IF($H4="","",IFERROR($H4*$P4,"")) | X4: =IF(OR($U4="",$W4=""),"",($U4+$V4)-$W4) | AQ4: =IF($B4="","",IF(OR(ISERROR(MATCH($B4,Community_Master!$A$2:$A$100,0)),$A4="",AND($H4<>"",$I4>$H4),AND($H4<>"",$J4>$H4),$I4<0,$J4<0,$K4<0,$P4<0,$Q4<0,$Y4<0,$Z4<0,$AA4<0,$AB4<0,$AC4<0),"ERROR","OK")) | AR4: =IF($B4="","",TRIM(IF(ISERROR(MATCH($B4,Community_Master!$A$2:$A$100,0)),"Invalid Community_ID; ","")&IF($A4="","Missing Report_Month; ","")&IF(AND($H4<>"",$I4>$H4),"Occupied_Units greater than Total_Units; ","")&IF(AND($H4<>"",$J4>$H4),"Leased_Units greater than Total_Units; ","")&IF($I4<0,"Occupied_Units negative; ","")&IF($J4<0,"Leased_Units negative; ","")&IF($P4<0,"Avg_Market_Rent negative; ","")))
C5: =IFERROR(VLOOKUP($B5,Community_Master!$A$2:$K$100,2,FALSE),"") | D5: =IFERROR(VLOOKUP($B5,Community_Master!$A$2:$K$100,4,FALSE),"") | E5: =IFERROR(VLOOKUP($B5,Community_Master!$A$2:$K$100,5,FALSE),"") | F5: =IFERROR(VLOOKUP($B5,Community_Master!$A$2:$K$100,6,FALSE),"") | G5: =IFERROR(VLOOKUP($B5,Community_Master!$A$2:$K$100,8,FALSE),"") | L5: =IF($H5="","",MAX($H5-$I5,0)) | M5: =IF($H5="","",IFERROR($I5/$H5,"")) | N5: =IF($H5="","",IFERROR($J5/$H5,"")) | T5: =IF($H5="","",IFERROR($H5*$P5,"")) | X5: =IF(OR($U5="",$W5=""),"",($U5+$V5)-$W5) | AQ5: =IF($B5="","",IF(OR(ISERROR(MATCH($B5,Community_Master!$A$2:$A$100,0)),$A5="",AND($H5<>"",$I5>$H5),AND($H5<>"",$J5>$H5),$I5<0,$J5<0,$K5<0,$P5<0,$Q5<0,$Y5<0,$Z5<0,$AA5<0,$AB5<0,$AC5<0),"ERROR","OK")) | AR5: =IF($B5="","",TRIM(IF(ISERROR(MATCH($B5,Community_Master!$A$2:$A$100,0)),"Invalid Community_ID; ","")&IF($A5="","Missing Report_Month; ","")&IF(AND($H5<>"",$I5>$H5),"Occupied_Units greater than Total_Units; ","")&IF(AND($H5<>"",$J5>$H5),"Leased_Units greater than Total_Units; ","")&IF($I5<0,"Occupied_Units negative; ","")&IF($J5<0,"Leased_Units negative; ","")&IF($P5<0,"Avg_Market_Rent negative; ","")))
C6: =IFERROR(VLOOKUP($B6,Community_Master!$A$2:$K$100,2,FALSE),"") | D6: =IFERROR(VLOOKUP($B6,Community_Master!$A$2:$K$100,4,FALSE),"") | E6: =IFERROR(VLOOKUP($B6,Community_Master!$A$2:$K$100,5,FALSE),"") | F6: =IFERROR(VLOOKUP($B6,Community_Master!$A$2:$K$100,6,FALSE),"") | G6: =IFERROR(VLOOKUP($B6,Community_Master!$A$2:$K$100,8,FALSE),"") | L6: =IF($H6="","",MAX($H6-$I6,0)) | M6: =IF($H6="","",IFERROR($I6/$H6,"")) | N6: =IF($H6="","",IFERROR($J6/$H6,"")) | T6: =IF($H6="","",IFERROR($H6*$P6,"")) | X6: =IF(OR($U6="",$W6=""),"",($U6+$V6)-$W6) | AQ6: =IF($B6="","",IF(OR(ISERROR(MATCH($B6,Community_Master!$A$2:$A$100,0)),$A6="",AND($H6<>"",$I6>$H6),AND($H6<>"",$J6>$H6),$I6<0,$J6<0,$K6<0,$P6<0,$Q6<0,$Y6<0,$Z6<0,$AA6<0,$AB6<0,$AC6<0),"ERROR","OK")) | AR6: =IF($B6="","",TRIM(IF(ISERROR(MATCH($B6,Community_Master!$A$2:$A$100,0)),"Invalid Community_ID; ","")&IF($A6="","Missing Report_Month; ","")&IF(AND($H6<>"",$I6>$H6),"Occupied_Units greater than Total_Units; ","")&IF(AND($H6<>"",$J6>$H6),"Leased_Units greater than Total_Units; ","")&IF($I6<0,"Occupied_Units negative; ","")&IF($J6<0,"Leased_Units negative; ","")&IF($P6<0,"Avg_Market_Rent negative; ","")))
C7: =IFERROR(VLOOKUP($B7,Community_Master!$A$2:$K$100,2,FALSE),"") | D7: =IFERROR(VLOOKUP($B7,Community_Master!$A$2:$K$100,4,FALSE),"") | E7: =IFERROR(VLOOKUP($B7,Community_Master!$A$2:$K$100,5,FALSE),"") | F7: =IFERROR(VLOOKUP($B7,Community_Master!$A$2:$K$100,6,FALSE),"") | G7: =IFERROR(VLOOKUP($B7,Community_Master!$A$2:$K$100,8,FALSE),"") | L7: =IF($H7="","",MAX($H7-$I7,0)) | M7: =IF($H7="","",IFERROR($I7/$H7,"")) | N7: =IF($H7="","",IFERROR($J7/$H7,"")) | T7: =IF($H7="","",IFERROR($H7*$P7,"")) | X7: =IF(OR($U7="",$W7=""),"",($U7+$V7)-$W7) | AQ7: =IF($B7="","",IF(OR(ISERROR(MATCH($B7,Community_Master!$A$2:$A$100,0)),$A7="",AND($H7<>"",$I7>$H7),AND($H7<>"",$J7>$H7),$I7<0,$J7<0,$K7<0,$P7<0,$Q7<0,$Y7<0,$Z7<0,$AA7<0,$AB7<0,$AC7<0),"ERROR","OK")) | AR7: =IF($B7="","",TRIM(IF(ISERROR(MATCH($B7,Community_Master!$A$2:$A$100,0)),"Invalid Community_ID; ","")&IF($A7="","Missing Report_Month; ","")&IF(AND($H7<>"",$I7>$H7),"Occupied_Units greater than Total_Units; ","")&IF(AND($H7<>"",$J7>$H7),"Leased_Units greater than Total_Units; ","")&IF($I7<0,"Occupied_Units negative; ","")&IF($J7<0,"Leased_Units negative; ","")&IF($P7<0,"Avg_Market_Rent negative; ","")))
C8: =IFERROR(VLOOKUP($B8,Community_Master!$A$2:$K$100,2,FALSE),"") | D8: =IFERROR(VLOOKUP($B8,Community_Master!$A$2:$K$100,4,FALSE),"") | E8: =IFERROR(VLOOKUP($B8,Community_Master!$A$2:$K$100,5,FALSE),"") | F8: =IFERROR(VLOOKUP($B8,Community_Master!$A$2:$K$100,6,FALSE),"") | G8: =IFERROR(VLOOKUP($B8,Community_Master!$A$2:$K$100,8,FALSE),"") | L8: =IF($H8="","",MAX($H8-$I8,0)) | M8: =IF($H8="","",IFERROR($I8/$H8,"")) | N8: =IF($H8="","",IFERROR($J8/$H8,"")) | T8: =IF($H8="","",IFERROR($H8*$P8,"")) | X8: =IF(OR($U8="",$W8=""),"",($U8+$V8)-$W8) | AQ8: =IF($B8="","",IF(OR(ISERROR(MATCH($B8,Community_Master!$A$2:$A$100,0)),$A8="",AND($H8<>"",$I8>$H8),AND($H8<>"",$J8>$H8),$I8<0,$J8<0,$K8<0,$P8<0,$Q8<0,$Y8<0,$Z8<0,$AA8<0,$AB8<0,$AC8<0),"ERROR","OK")) | AR8: =IF($B8="","",TRIM(IF(ISERROR(MATCH($B8,Community_Master!$A$2:$A$100,0)),"Invalid Community_ID; ","")&IF($A8="","Missing Report_Month; ","")&IF(AND($H8<>"",$I8>$H8),"Occupied_Units greater than Total_Units; ","")&IF(AND($H8<>"",$J8>$H8),"Leased_Units greater than Total_Units; ","")&IF($I8<0,"Occupied_Units negative; ","")&IF($J8<0,"Leased_Units negative; ","")&IF($P8<0,"Avg_Market_Rent negative; ","")))
C9: =IFERROR(VLOOKUP($B9,Community_Master!$A$2:$K$100,2,FALSE),"") | D9: =IFERROR(VLOOKUP($B9,Community_Master!$A$2:$K$100,4,FALSE),"") | E9: =IFERROR(VLOOKUP($B9,Community_Master!$A$2:$K$100,5,FALSE),"") | F9: =IFERROR(VLOOKUP($B9,Community_Master!$A$2:$K$100,6,FALSE),"") | G9: =IFERROR(VLOOKUP($B9,Community_Master!$A$2:$K$100,8,FALSE),"") | L9: =IF($H9="","",MAX($H9-$I9,0)) | M9: =IF($H9="","",IFERROR($I9/$H9,"")) | N9: =IF($H9="","",IFERROR($J9/$H9,"")) | T9: =IF($H9="","",IFERROR($H9*$P9,"")) | X9: =IF(OR($U9="",$W9=""),"",($U9+$V9)-$W9) | AQ9: =IF($B9="","",IF(OR(ISERROR(MATCH($B9,Community_Master!$A$2:$A$100,0)),$A9="",AND($H9<>"",$I9>$H9),AND($H9<>"",$J9>$H9),$I9<0,$J9<0,$K9<0,$P9<0,$Q9<0,$Y9<0,$Z9<0,$AA9<0,$AB9<0,$AC9<0),"ERROR","OK")) | AR9: =IF($B9="","",TRIM(IF(ISERROR(MATCH($B9,Community_Master!$A$2:$A$100,0)),"Invalid Community_ID; ","")&IF($A9="","Missing Report_Month; ","")&IF(AND($H9<>"",$I9>$H9),"Occupied_Units greater than Total_Units; ","")&IF(AND($H9<>"",$J9>$H9),"Leased_Units greater than Total_Units; ","")&IF($I9<0,"Occupied_Units negative; ","")&IF($J9<0,"Leased_Units negative; ","")&IF($P9<0,"Avg_Market_Rent negative; ","")))
C10: =IFERROR(VLOOKUP($B10,Community_Master!$A$2:$K$100,2,FALSE),"") | D10: =IFERROR(VLOOKUP($B10,Community_Master!$A$2:$K$100,4,FALSE),"") | E10: =IFERROR(VLOOKUP($B10,Community_Master!$A$2:$K$100,5,FALSE),"") | F10: =IFERROR(VLOOKUP($B10,Community_Master!$A$2:$K$100,6,FALSE),"") | G10: =IFERROR(VLOOKUP($B10,Community_Master!$A$2:$K$100,8,FALSE),"") | L10: =IF($H10="","",MAX($H10-$I10,0)) | M10: =IF($H10="","",IFERROR($I10/$H10,"")) | N10: =IF($H10="","",IFERROR($J10/$H10,"")) | T10: =IF($H10="","",IFERROR($H10*$P10,"")) | X10: =IF(OR($U10="",$W10=""),"",($U10+$V10)-$W10) | AQ10: =IF($B10="","",IF(OR(ISERROR(MATCH($B10,Community_Master!$A$2:$A$100,0)),$A10="",AND($H10<>"",$I10>$H10),AND($H10<>"",$J10>$H10),$I10<0,$J10<0,$K10<0,$P10<0,$Q10<0,$Y10<0,$Z10<0,$AA10<0,$AB10<0,$AC10<0),"ERROR","OK")) | AR10: =IF($B10="","",TRIM(IF(ISERROR(MATCH($B10,Community_Master!$A$2:$A$100,0)),"Invalid Community_ID; ","")&IF($A10="","Missing Report_Month; ","")&IF(AND($H10<>"",$I10>$H10),"Occupied_Units greater than Total_Units; ","")&IF(AND($H10<>"",$J10>$H10),"Leased_Units greater than Total_Units; ","")&IF($I10<0,"Occupied_Units negative; ","")&IF($J10<0,"Leased_Units negative; ","")&IF($P10<0,"Avg_Market_Rent negative; ","")))
C11: =IFERROR(VLOOKUP($B11,Community_Master!$A$2:$K$100,2,FALSE),"") | D11: =IFERROR(VLOOKUP($B11,Community_Master!$A$2:$K$100,4,FALSE),"") | E11: =IFERROR(VLOOKUP($B11,Community_Master!$A$2:$K$100,5,FALSE),"") | F11: =IFERROR(VLOOKUP($B11,Community_Master!$A$2:$K$100,6,FALSE),"") | G11: =IFERROR(VLOOKUP($B11,Community_Master!$A$2:$K$100,8,FALSE),"") | L11: =IF($H11="","",MAX($H11-$I11,0)) | M11: =IF($H11="","",IFERROR($I11/$H11,"")) | N11: =IF($H11="","",IFERROR($J11/$H11,"")) | T11: =IF($H11="","",IFERROR($H11*$P11,"")) | X11: =IF(OR($U11="",$W11=""),"",($U11+$V11)-$W11) | AQ11: =IF($B11="","",IF(OR(ISERROR(MATCH($B11,Community_Master!$A$2:$A$100,0)),$A11="",AND($H11<>"",$I11>$H11),AND($H11<>"",$J11>$H11),$I11<0,$J11<0,$K11<0,$P11<0,$Q11<0,$Y11<0,$Z11<0,$AA11<0,$AB11<0,$AC11<0),"ERROR","OK")) | AR11: =IF($B11="","",TRIM(IF(ISERROR(MATCH($B11,Community_Master!$A$2:$A$100,0)),"Invalid Community_ID; ","")&IF($A11="","Missing Report_Month; ","")&IF(AND($H11<>"",$I11>$H11),"Occupied_Units greater than Total_Units; ","")&IF(AND($H11<>"",$J11>$H11),"Leased_Units greater than Total_Units; ","")&IF($I11<0,"Occupied_Units negative; ","")&IF($J11<0,"Leased_Units negative; ","")&IF($P11<0,"Avg_Market_Rent negative; ","")))
C12: =IFERROR(VLOOKUP($B12,Community_Master!$A$2:$K$100,2,FALSE),"") | D12: =IFERROR(VLOOKUP($B12,Community_Master!$A$2:$K$100,4,FALSE),"") | E12: =IFERROR(VLOOKUP($B12,Community_Master!$A$2:$K$100,5,FALSE),"") | F12: =IFERROR(VLOOKUP($B12,Community_Master!$A$2:$K$100,6,FALSE),"") | G12: =IFERROR(VLOOKUP($B12,Community_Master!$A$2:$K$100,8,FALSE),"") | L12: =IF($H12="","",MAX($H12-$I12,0)) | M12: =IF($H12="","",IFERROR($I12/$H12,"")) | N12: =IF($H12="","",IFERROR($J12/$H12,"")) | T12: =IF($H12="","",IFERROR($H12*$P12,"")) | X12: =IF(OR($U12="",$W12=""),"",($U12+$V12)-$W12) | AQ12: =IF($B12="","",IF(OR(ISERROR(MATCH($B12,Community_Master!$A$2:$A$100,0)),$A12="",AND($H12<>"",$I12>$H12),AND($H12<>"",$J12>$H12),$I12<0,$J12<0,$K12<0,$P12<0,$Q12<0,$Y12<0,$Z12<0,$AA12<0,$AB12<0,$AC12<0),"ERROR","OK")) | AR12: =IF($B12="","",TRIM(IF(ISERROR(MATCH($B12,Community_Master!$A$2:$A$100,0)),"Invalid Community_ID; ","")&IF($A12="","Missing Report_Month; ","")&IF(AND($H12<>"",$I12>$H12),"Occupied_Units greater than Total_Units; ","")&IF(AND($H12<>"",$J12>$H12),"Leased_Units greater than Total_Units; ","")&IF($I12<0,"Occupied_Units negative; ","")&IF($J12<0,"Leased_Units negative; ","")&IF($P12<0,"Avg_Market_Rent negative; ","")))
C13: =IFERROR(VLOOKUP($B13,Community_Master!$A$2:$K$100,2,FALSE),"") | D13: =IFERROR(VLOOKUP($B13,Community_Master!$A$2:$K$100,4,FALSE),"") | E13: =IFERROR(VLOOKUP($B13,Community_Master!$A$2:$K$100,5,FALSE),"") | F13: =IFERROR(VLOOKUP($B13,Community_Master!$A$2:$K$100,6,FALSE),"") | G13: =IFERROR(VLOOKUP($B13,Community_Master!$A$2:$K$100,8,FALSE),"") | L13: =IF($H13="","",MAX($H13-$I13,0)) | M13: =IF($H13="","",IFERROR($I13/$H13,"")) | N13: =IF($H13="","",IFERROR($J13/$H13,"")) | T13: =IF($H13="","",IFERROR($H13*$P13,"")) | X13: =IF(OR($U13="",$W13=""),"",($U13+$V13)-$W13) | AQ13: =IF($B13="","",IF(OR(ISERROR(MATCH($B13,Community_Master!$A$2:$A$100,0)),$A13="",AND($H13<>"",$I13>$H13),AND($H13<>"",$J13>$H13),$I13<0,$J13<0,$K13<0,$P13<0,$Q13<0,$Y13<0,$Z13<0,$AA13<0,$AB13<0,$AC13<0),"ERROR","OK")) | AR13: =IF($B13="","",TRIM(IF(ISERROR(MATCH($B13,Community_Master!$A$2:$A$100,0)),"Invalid Community_ID; ","")&IF($A13="","Missing Report_Month; ","")&IF(AND($H13<>"",$I13>$H13),"Occupied_Units greater than Total_Units; ","")&IF(AND($H13<>"",$J13>$H13),"Leased_Units greater than Total_Units; ","")&IF($I13<0,"Occupied_Units negative; ","")&IF($J13<0,"Leased_Units negative; ","")&IF($P13<0,"Avg_Market_Rent negative; ","")))
C14: =IFERROR(VLOOKUP($B14,Community_Master!$A$2:$K$100,2,FALSE),"") | D14: =IFERROR(VLOOKUP($B14,Community_Master!$A$2:$K$100,4,FALSE),"") | E14: =IFERROR(VLOOKUP($B14,Community_Master!$A$2:$K$100,5,FALSE),"") | F14: =IFERROR(VLOOKUP($B14,Community_Master!$A$2:$K$100,6,FALSE),"") | G14: =IFERROR(VLOOKUP($B14,Community_Master!$A$2:$K$100,8,FALSE),"") | L14: =IF($H14="","",MAX($H14-$I14,0)) | M14: =IF($H14="","",IFERROR($I14/$H14,"")) | N14: =IF($H14="","",IFERROR($J14/$H14,"")) | T14: =IF($H14="","",IFERROR($H14*$P14,"")) | X14: =IF(OR($U14="",$W14=""),"",($U14+$V14)-$W14) | AQ14: =IF($B14="","",IF(OR(ISERROR(MATCH($B14,Community_Master!$A$2:$A$100,0)),$A14="",AND($H14<>"",$I14>$H14),AND($H14<>"",$J14>$H14),$I14<0,$J14<0,$K14<0,$P14<0,$Q14<0,$Y14<0,$Z14<0,$AA14<0,$AB14<0,$AC14<0),"ERROR","OK")) | AR14: =IF($B14="","",TRIM(IF(ISERROR(MATCH($B14,Community_Master!$A$2:$A$100,0)),"Invalid Community_ID; ","")&IF($A14="","Missing Report_Month; ","")&IF(AND($H14<>"",$I14>$H14),"Occupied_Units greater than Total_Units; ","")&IF(AND($H14<>"",$J14>$H14),"Leased_Units greater than Total_Units; ","")&IF($I14<0,"Occupied_Units negative; ","")&IF($J14<0,"Leased_Units negative; ","")&IF($P14<0,"Avg_Market_Rent negative; ","")))
... C30: =IFERROR(VLOOKUP($B30,Community_Master!$A$2:$K$100,2,FALSE),"") | D30: =IFERROR(VLOOKUP($B30,Community_Master!$A$2:$K$100,4,FALSE),"") | E30: =IFERROR(VLOOKUP($B30,Community_Master!$A$2:$K$100,5,FALSE),"") | F30: =IFERROR(VLOOKUP($B30,Community_Master!$A$2:$K$100,6,FALSE),"") | G30: =IFERROR(VLOOKUP($B30,Community_Master!$A$2:$K$100,8,FALSE),"") | L30: =IF($H30="","",MAX($H30-$I30,0)) | M30: =IF($H30="","",IFERROR($I30/$H30,"")) | N30: =IF($H30="","",IFERROR($J30/$H30,"")) | T30: =IF($H30="","",IFERROR($H30*$P30,"")) | X30: =IF(OR($U30="",$W30=""),"",($U30+$V30)-$W30) | AQ30: =IF($B30="","",IF(OR(ISERROR(MATCH($B30,Community_Master!$A$2:$A$100,0)),$A30="",AND($H30<>"",$I30>$H30),AND($H30<>"",$J30>$H30),$I30<0,$J30<0,$K30<0,$P30<0,$Q30<0,$Y30<0,$Z30<0,$AA30<0,$AB30<0,$AC30<0),"ERROR","OK")) | AR30: =IF($B30="","",TRIM(IF(ISERROR(MATCH($B30,Community_Master!$A$2:$A$100,0)),"Invalid Community_ID; ","")&IF($A30="","Missing Report_Month; ","")&IF(AND($H30<>"",$I30>$H30),"Occupied_Units greater than Total_Units; ","")&IF(AND($H30<>"",$J30>$H30),"Leased_Units greater than Total_Units; ","")&IF($I30<0,"Occupied_Units negative; ","")&IF($J30<0,"Leased_Units negative; ","")&IF($P30<0,"Avg_Market_Rent negative; ","")))
C31: =IFERROR(VLOOKUP($B31,Community_Master!$A$2:$K$100,2,FALSE),"") | D31: =IFERROR(VLOOKUP($B31,Community_Master!$A$2:$K$100,4,FALSE),"") | E31: =IFERROR(VLOOKUP($B31,Community_Master!$A$2:$K$100,5,FALSE),"") | F31: =IFERROR(VLOOKUP($B31,Community_Master!$A$2:$K$100,6,FALSE),"") | G31: =IFERROR(VLOOKUP($B31,Community_Master!$A$2:$K$100,8,FALSE),"") | H31: =IFERROR(VLOOKUP($B31,Community_Master!$A$2:$K$100,7,FALSE),"") | L31: =IF($H31="","",MAX($H31-$I31,0)) | M31: =IF($H31="","",IFERROR($I31/$H31,"")) | N31: =IF($H31="","",IFERROR($J31/$H31,"")) | T31: =IF($H31="","",IFERROR($H31*$P31,"")) | X31: =IF(OR($U31="",$W31=""),"",($U31+$V31)-$W31) | AQ31: =IF($B31="","",IF(OR(ISERROR(MATCH($B31,Community_Master!$A$2:$A$100,0)),$A31="",AND($H31<>"",$I31>$H31),AND($H31<>"",$J31>$H31),$I31<0,$J31<0,$K31<0,$P31<0,$Q31<0,$Y31<0,$Z31<0,$AA31<0,$AB31<0,$AC31<0),"ERROR","OK")) | AR31: =IF($B31="","",TRIM(IF(ISERROR(MATCH($B31,Community_Master!$A$2:$A$100,0)),"Invalid Community_ID; ","")&IF($A31="","Missing Report_Month; ","")&IF(AND($H31<>"",$I31>$H31),"Occupied_Units greater than Total_Units; ","")&IF(AND($H31<>"",$J31>$H31),"Leased_Units greater than Total_Units; ","")&IF($I31<0,"Occupied_Units negative; ","")&IF($J31<0,"Leased_Units negative; ","")&IF($P31<0,"Avg_Market_Rent negative; ","")))
C32: =IFERROR(VLOOKUP($B32,Community_Master!$A$2:$K$100,2,FALSE),"") | D32: =IFERROR(VLOOKUP($B32,Community_Master!$A$2:$K$100,4,FALSE),"") | E32: =IFERROR(VLOOKUP($B32,Community_Master!$A$2:$K$100,5,FALSE),"") | F32: =IFERROR(VLOOKUP($B32,Community_Master!$A$2:$K$100,6,FALSE),"") | G32: =IFERROR(VLOOKUP($B32,Community_Master!$A$2:$K$100,8,FALSE),"") | H32: =IFERROR(VLOOKUP($B32,Community_Master!$A$2:$K$100,7,FALSE),"") | L32: =IF($H32="","",MAX($H32-$I32,0)) | M32: =IF($H32="","",IFERROR($I32/$H32,"")) | N32: =IF($H32="","",IFERROR($J32/$H32,"")) | T32: =IF($H32="","",IFERROR($H32*$P32,"")) | X32: =IF(OR($U32="",$W32=""),"",($U32+$V32)-$W32) | AQ32: =IF($B32="","",IF(OR(ISERROR(MATCH($B32,Community_Master!$A$2:$A$100,0)),$A32="",AND($H32<>"",$I32>$H32),AND($H32<>"",$J32>$H32),$I32<0,$J32<0,$K32<0,$P32<0,$Q32<0,$Y32<0,$Z32<0,$AA32<0,$AB32<0,$AC32<0),"ERROR","OK")) | AR32: =IF($B32="","",TRIM(IF(ISERROR(MATCH($B32,Community_Master!$A$2:$A$100,0)),"Invalid Community_ID; ","")&IF($A32="","Missing Report_Month; ","")&IF(AND($H32<>"",$I32>$H32),"Occupied_Units greater than Total_Units; ","")&IF(AND($H32<>"",$J32>$H32),"Leased_Units greater than Total_Units; ","")&IF($I32<0,"Occupied_Units negative; ","")&IF($J32<0,"Leased_Units negative; ","")&IF($P32<0,"Avg_Market_Rent negative; ","")))
C33: =IFERROR(VLOOKUP($B33,Community_Master!$A$2:$K$100,2,FALSE),"") | D33: =IFERROR(VLOOKUP($B33,Community_Master!$A$2:$K$100,4,FALSE),"") | E33: =IFERROR(VLOOKUP($B33,Community_Master!$A$2:$K$100,5,FALSE),"") | F33: =IFERROR(VLOOKUP($B33,Community_Master!$A$2:$K$100,6,FALSE),"") | G33: =IFERROR(VLOOKUP($B33,Community_Master!$A$2:$K$100,8,FALSE),"") | H33: =IFERROR(VLOOKUP($B33,Community_Master!$A$2:$K$100,7,FALSE),"") | L33: =IF($H33="","",MAX($H33-$I33,0)) | M33: =IF($H33="","",IFERROR($I33/$H33,"")) | N33: =IF($H33="","",IFERROR($J33/$H33,"")) | T33: =IF($H33="","",IFERROR($H33*$P33,"")) | X33: =IF(OR($U33="",$W33=""),"",($U33+$V33)-$W33) | AQ33: =IF($B33="","",IF(OR(ISERROR(MATCH($B33,Community_Master!$A$2:$A$100,0)),$A33="",AND($H33<>"",$I33>$H33),AND($H33<>"",$J33>$H33),$I33<0,$J33<0,$K33<0,$P33<0,$Q33<0,$Y33<0,$Z33<0,$AA33<0,$AB33<0,$AC33<0),"ERROR","OK")) | AR33: =IF($B33="","",TRIM(IF(ISERROR(MATCH($B33,Community_Master!$A$2:$A$100,0)),"Invalid Community_ID; ","")&IF($A33="","Missing Report_Month; ","")&IF(AND($H33<>"",$I33>$H33),"Occupied_Units greater than Total_Units; ","")&IF(AND($H33<>"",$J33>$H33),"Leased_Units greater than Total_Units; ","")&IF($I33<0,"Occupied_Units negative; ","")&IF($J33<0,"Leased_Units negative; ","")&IF($P33<0,"Avg_Market_Rent negative; ","")))
C34: =IFERROR(VLOOKUP($B34,Community_Master!$A$2:$K$100,2,FALSE),"") | D34: =IFERROR(VLOOKUP($B34,Community_Master!$A$2:$K$100,4,FALSE),"") | E34: =IFERROR(VLOOKUP($B34,Community_Master!$A$2:$K$100,5,FALSE),"") | F34: =IFERROR(VLOOKUP($B34,Community_Master!$A$2:$K$100,6,FALSE),"") | G34: =IFERROR(VLOOKUP($B34,Community_Master!$A$2:$K$100,8,FALSE),"") | H34: =IFERROR(VLOOKUP($B34,Community_Master!$A$2:$K$100,7,FALSE),"") | L34: =IF($H34="","",MAX($H34-$I34,0)) | M34: =IF($H34="","",IFERROR($I34/$H34,"")) | N34: =IF($H34="","",IFERROR($J34/$H34,"")) | T34: =IF($H34="","",IFERROR($H34*$P34,"")) | X34: =IF(OR($U34="",$W34=""),"",($U34+$V34)-$W34) | AQ34: =IF($B34="","",IF(OR(ISERROR(MATCH($B34,Community_Master!$A$2:$A$100,0)),$A34="",AND($H34<>"",$I34>$H34),AND($H34<>"",$J34>$H34),$I34<0,$J34<0,$K34<0,$P34<0,$Q34<0,$Y34<0,$Z34<0,$AA34<0,$AB34<0,$AC34<0),"ERROR","OK")) | AR34: =IF($B34="","",TRIM(IF(ISERROR(MATCH($B34,Community_Master!$A$2:$A$100,0)),"Invalid Community_ID; ","")&IF($A34="","Missing Report_Month; ","")&IF(AND($H34<>"",$I34>$H34),"Occupied_Units greater than Total_Units; ","")&IF(AND($H34<>"",$J34>$H34),"Leased_Units greater than Total_Units; ","")&IF($I34<0,"Occupied_Units negative; ","")&IF($J34<0,"Leased_Units negative; ","")&IF($P34<0,"Avg_Market_Rent negative; ","")))
C35: =IFERROR(VLOOKUP($B35,Community_Master!$A$2:$K$100,2,FALSE),"") | D35: =IFERROR(VLOOKUP($B35,Community_Master!$A$2:$K$100,4,FALSE),"") | E35: =IFERROR(VLOOKUP($B35,Community_Master!$A$2:$K$100,5,FALSE),"") | F35: =IFERROR(VLOOKUP($B35,Community_Master!$A$2:$K$100,6,FALSE),"") | G35: =IFERROR(VLOOKUP($B35,Community_Master!$A$2:$K$100,8,FALSE),"") | H35: =IFERROR(VLOOKUP($B35,Community_Master!$A$2:$K$100,7,FALSE),"") | L35: =IF($H35="","",MAX($H35-$I35,0)) | M35: =IF($H35="","",IFERROR($I35/$H35,"")) | N35: =IF($H35="","",IFERROR($J35/$H35,"")) | T35: =IF($H35="","",IFERROR($H35*$P35,"")) | X35: =IF(OR($U35="",$W35=""),"",($U35+$V35)-$W35) | AQ35: =IF($B35="","",IF(OR(ISERROR(MATCH($B35,Community_Master!$A$2:$A$100,0)),$A35="",AND($H35<>"",$I35>$H35),AND($H35<>"",$J35>$H35),$I35<0,$J35<0,$K35<0,$P35<0,$Q35<0,$Y35<0,$Z35<0,$AA35<0,$AB35<0,$AC35<0),"ERROR","OK")) | AR35: =IF($B35="","",TRIM(IF(ISERROR(MATCH($B35,Community_Master!$A$2:$A$100,0)),"Invalid Community_ID; ","")&IF($A35="","Missing Report_Month; ","")&IF(AND($H35<>"",$I35>$H35),"Occupied_Units greater than Total_Units; ","")&IF(AND($H35<>"",$J35>$H35),"Leased_Units greater than Total_Units; ","")&IF($I35<0,"Occupied_Units negative; ","")&IF($J35<0,"Leased_Units negative; ","")&IF($P35<0,"Avg_Market_Rent negative; ","")))
C36: =IFERROR(VLOOKUP($B36,Community_Master!$A$2:$K$100,2,FALSE),"") | D36: =IFERROR(VLOOKUP($B36,Community_Master!$A$2:$K$100,4,FALSE),"") | E36: =IFERROR(VLOOKUP($B36,Community_Master!$A$2:$K$100,5,FALSE),"") | F36: =IFERROR(VLOOKUP($B36,Community_Master!$A$2:$K$100,6,FALSE),"") | G36: =IFERROR(VLOOKUP($B36,Community_Master!$A$2:$K$100,8,FALSE),"") | H36: =IFERROR(VLOOKUP($B36,Community_Master!$A$2:$K$100,7,FALSE),"") | L36: =IF($H36="","",MAX($H36-$I36,0)) | M36: =IF($H36="","",IFERROR($I36/$H36,"")) | N36: =IF($H36="","",IFERROR($J36/$H36,"")) | T36: =IF($H36="","",IFERROR($H36*$P36,"")) | X36: =IF(OR($U36="",$W36=""),"",($U36+$V36)-$W36) | AQ36: =IF($B36="","",IF(OR(ISERROR(MATCH($B36,Community_Master!$A$2:$A$100,0)),$A36="",AND($H36<>"",$I36>$H36),AND($H36<>"",$J36>$H36),$I36<0,$J36<0,$K36<0,$P36<0,$Q36<0,$Y36<0,$Z36<0,$AA36<0,$AB36<0,$AC36<0),"ERROR","OK")) | AR36: =IF($B36="","",TRIM(IF(ISERROR(MATCH($B36,Community_Master!$A$2:$A$100,0)),"Invalid Community_ID; ","")&IF($A36="","Missing Report_Month; ","")&IF(AND($H36<>"",$I36>$H36),"Occupied_Units greater than Total_Units; ","")&IF(AND($H36<>"",$J36>$H36),"Leased_Units greater than Total_Units; ","")&IF($I36<0,"Occupied_Units negative; ","")&IF($J36<0,"Leased_Units negative; ","")&IF($P36<0,"Avg_Market_Rent negative; ","")))
C37: =IFERROR(VLOOKUP($B37,Community_Master!$A$2:$K$100,2,FALSE),"") | D37: =IFERROR(VLOOKUP($B37,Community_Master!$A$2:$K$100,4,FALSE),"") | E37: =IFERROR(VLOOKUP($B37,Community_Master!$A$2:$K$100,5,FALSE),"") | F37: =IFERROR(VLOOKUP($B37,Community_Master!$A$2:$K$100,6,FALSE),"") | G37: =IFERROR(VLOOKUP($B37,Community_Master!$A$2:$K$100,8,FALSE),"") | H37: =IFERROR(VLOOKUP($B37,Community_Master!$A$2:$K$100,7,FALSE),"") | L37: =IF($H37="","",MAX($H37-$I37,0)) | M37: =IF($H37="","",IFERROR($I37/$H37,"")) | N37: =IF($H37="","",IFERROR($J37/$H37,"")) | T37: =IF($H37="","",IFERROR($H37*$P37,"")) | X37: =IF(OR($U37="",$W37=""),"",($U37+$V37)-$W37) | AQ37: =IF($B37="","",IF(OR(ISERROR(MATCH($B37,Community_Master!$A$2:$A$100,0)),$A37="",AND($H37<>"",$I37>$H37),AND($H37<>"",$J37>$H37),$I37<0,$J37<0,$K37<0,$P37<0,$Q37<0,$Y37<0,$Z37<0,$AA37<0,$AB37<0,$AC37<0),"ERROR","OK")) | AR37: =IF($B37="","",TRIM(IF(ISERROR(MATCH($B37,Community_Master!$A$2:$A$100,0)),"Invalid Community_ID; ","")&IF($A37="","Missing Report_Month; ","")&IF(AND($H37<>"",$I37>$H37),"Occupied_Units greater than Total_Units; ","")&IF(AND($H37<>"",$J37>$H37),"Leased_Units greater than Total_Units; ","")&IF($I37<0,"Occupied_Units negative; ","")&IF($J37<0,"Leased_Units negative; ","")&IF($P37<0,"Avg_Market_Rent negative; ","")))
C38: =IFERROR(VLOOKUP($B38,Community_Master!$A$2:$K$100,2,FALSE),"") | D38: =IFERROR(VLOOKUP($B38,Community_Master!$A$2:$K$100,4,FALSE),"") | E38: =IFERROR(VLOOKUP($B38,Community_Master!$A$2:$K$100,5,FALSE),"") | F38: =IFERROR(VLOOKUP($B38,Community_Master!$A$2:$K$100,6,FALSE),"") | G38: =IFERROR(VLOOKUP($B38,Community_Master!$A$2:$K$100,8,FALSE),"") | H38: =IFERROR(VLOOKUP($B38,Community_Master!$A$2:$K$100,7,FALSE),"") | L38: =IF($H38="","",MAX($H38-$I38,0)) | M38: =IF($H38="","",IFERROR($I38/$H38,"")) | N38: =IF($H38="","",IFERROR($J38/$H38,"")) | T38: =IF($H38="","",IFERROR($H38*$P38,"")) | X38: =IF(OR($U38="",$W38=""),"",($U38+$V38)-$W38) | AQ38: =IF($B38="","",IF(OR(ISERROR(MATCH($B38,Community_Master!$A$2:$A$100,0)),$A38="",AND($H38<>"",$I38>$H38),AND($H38<>"",$J38>$H38),$I38<0,$J38<0,$K38<0,$P38<0,$Q38<0,$Y38<0,$Z38<0,$AA38<0,$AB38<0,$AC38<0),"ERROR","OK")) | AR38: =IF($B38="","",TRIM(IF(ISERROR(MATCH($B38,Community_Master!$A$2:$A$100,0)),"Invalid Community_ID; ","")&IF($A38="","Missing Report_Month; ","")&IF(AND($H38<>"",$I38>$H38),"Occupied_Units greater than Total_Units; ","")&IF(AND($H38<>"",$J38>$H38),"Leased_Units greater than Total_Units; ","")&IF($I38<0,"Occupied_Units negative; ","")&IF($J38<0,"Leased_Units negative; ","")&IF($P38<0,"Avg_Market_Rent negative; ","")))
C39: =IFERROR(VLOOKUP($B39,Community_Master!$A$2:$K$100,2,FALSE),"") | D39: =IFERROR(VLOOKUP($B39,Community_Master!$A$2:$K$100,4,FALSE),"") | E39: =IFERROR(VLOOKUP($B39,Community_Master!$A$2:$K$100,5,FALSE),"") | F39: =IFERROR(VLOOKUP($B39,Community_Master!$A$2:$K$100,6,FALSE),"") | G39: =IFERROR(VLOOKUP($B39,Community_Master!$A$2:$K$100,8,FALSE),"") | H39: =IFERROR(VLOOKUP($B39,Community_Master!$A$2:$K$100,7,FALSE),"") | L39: =IF($H39="","",MAX($H39-$I39,0)) | M39: =IF($H39="","",IFERROR($I39/$H39,"")) | N39: =IF($H39="","",IFERROR($J39/$H39,"")) | T39: =IF($H39="","",IFERROR($H39*$P39,"")) | X39: =IF(OR($U39="",$W39=""),"",($U39+$V39)-$W39) | AQ39: =IF($B39="","",IF(OR(ISERROR(MATCH($B39,Community_Master!$A$2:$A$100,0)),$A39="",AND($H39<>"",$I39>$H39),AND($H39<>"",$J39>$H39),$I39<0,$J39<0,$K39<0,$P39<0,$Q39<0,$Y39<0,$Z39<0,$AA39<0,$AB39<0,$AC39<0),"ERROR","OK")) | AR39: =IF($B39="","",TRIM(IF(ISERROR(MATCH($B39,Community_Master!$A$2:$A$100,0)),"Invalid Community_ID; ","")&IF($A39="","Missing Report_Month; ","")&IF(AND($H39<>"",$I39>$H39),"Occupied_Units greater than Total_Units; ","")&IF(AND($H39<>"",$J39>$H39),"Leased_Units greater than Total_Units; ","")&IF($I39<0,"Occupied_Units negative; ","")&IF($J39<0,"Leased_Units negative; ","")&IF($P39<0,"Avg_Market_Rent negative; ","")))
C40: =IFERROR(VLOOKUP($B40,Community_Master!$A$2:$K$100,2,FALSE),"") | D40: =IFERROR(VLOOKUP($B40,Community_Master!$A$2:$K$100,4,FALSE),"") | E40: =IFERROR(VLOOKUP($B40,Community_Master!$A$2:$K$100,5,FALSE),"") | F40: =IFERROR(VLOOKUP($B40,Community_Master!$A$2:$K$100,6,FALSE),"") | G40: =IFERROR(VLOOKUP($B40,Community_Master!$A$2:$K$100,8,FALSE),"") | H40: =IFERROR(VLOOKUP($B40,Community_Master!$A$2:$K$100,7,FALSE),"") | L40: =IF($H40="","",MAX($H40-$I40,0)) | M40: =IF($H40="","",IFERROR($I40/$H40,"")) | N40: =IF($H40="","",IFERROR($J40/$H40,"")) | T40: =IF($H40="","",IFERROR($H40*$P40,"")) | X40: =IF(OR($U40="",$W40=""),"",($U40+$V40)-$W40) | AQ40: =IF($B40="","",IF(OR(ISERROR(MATCH($B40,Community_Master!$A$2:$A$100,0)),$A40="",AND($H40<>"",$I40>$H40),AND($H40<>"",$J40>$H40),$I40<0,$J40<0,$K40<0,$P40<0,$Q40<0,$Y40<0,$Z40<0,$AA40<0,$AB40<0,$AC40<0),"ERROR","OK")) | AR40: =IF($B40="","",TRIM(IF(ISERROR(MATCH($B40,Community_Master!$A$2:$A$100,0)),"Invalid Community_ID; ","")&IF($A40="","Missing Report_Month; ","")&IF(AND($H40<>"",$I40>$H40),"Occupied_Units greater than Total_Units; ","")&IF(AND($H40<>"",$J40>$H40),"Leased_Units greater than Total_Units; ","")&IF($I40<0,"Occupied_Units negative; ","")&IF($J40<0,"Leased_Units negative; ","")&IF($P40<0,"Avg_Market_Rent negative; ","")))
C41: =IFERROR(VLOOKUP($B41,Community_Master!$A$2:$K$100,2,FALSE),"") | D41: =IFERROR(VLOOKUP($B41,Community_Master!$A$2:$K$100,4,FALSE),"") | E41: =IFERROR(VLOOKUP($B41,Community_Master!$A$2:$K$100,5,FALSE),"") | F41: =IFERROR(VLOOKUP($B41,Community_Master!$A$2:$K$100,6,FALSE),"") | G41: =IFERROR(VLOOKUP($B41,Community_Master!$A$2:$K$100,8,FALSE),"") | H41: =IFERROR(VLOOKUP($B41,Community_Master!$A$2:$K$100,7,FALSE),"") | L41: =IF($H41="","",MAX($H41-$I41,0)) | M41: =IF($H41="","",IFERROR($I41/$H41,"")) | N41: =IF($H41="","",IFERROR($J41/$H41,"")) | T41: =IF($H41="","",IFERROR($H41*$P41,"")) | X41: =IF(OR($U41="",$W41=""),"",($U41+$V41)-$W41) | AQ41: =IF($B41="","",IF(OR(ISERROR(MATCH($B41,Community_Master!$A$2:$A$100,0)),$A41="",AND($H41<>"",$I41>$H41),AND($H41<>"",$J41>$H41),$I41<0,$J41<0,$K41<0,$P41<0,$Q41<0,$Y41<0,$Z41<0,$AA41<0,$AB41<0,$AC41<0),"ERROR","OK")) | AR41: =IF($B41="","",TRIM(IF(ISERROR(MATCH($B41,Community_Master!$A$2:$A$100,0)),"Invalid Community_ID; ","")&IF($A41="","Missing Report_Month; ","")&IF(AND($H41<>"",$I41>$H41),"Occupied_Units greater than Total_Units; ","")&IF(AND($H41<>"",$J41>$H41),"Leased_Units greater than Total_Units; ","")&IF($I41<0,"Occupied_Units negative; ","")&IF($J41<0,"Leased_Units negative; ","")&IF($P41<0,"Avg_Market_Rent negative; ","")))
C42: =IFERROR(VLOOKUP($B42,Community_Master!$A$2:$K$100,2,FALSE),"") | D42: =IFERROR(VLOOKUP($B42,Community_Master!$A$2:$K$100,4,FALSE),"") | E42: =IFERROR(VLOOKUP($B42,Community_Master!$A$2:$K$100,5,FALSE),"") | F42: =IFERROR(VLOOKUP($B42,Community_Master!$A$2:$K$100,6,FALSE),"") | G42: =IFERROR(VLOOKUP($B42,Community_Master!$A$2:$K$100,8,FALSE),"") | H42: =IFERROR(VLOOKUP($B42,Community_Master!$A$2:$K$100,7,FALSE),"") | L42: =IF($H42="","",MAX($H42-$I42,0)) | M42: =IF($H42="","",IFERROR($I42/$H42,"")) | N42: =IF($H42="","",IFERROR($J42/$H42,"")) | T42: =IF($H42="","",IFERROR($H42*$P42,"")) | X42: =IF(OR($U42="",$W42=""),"",($U42+$V42)-$W42) | AQ42: =IF($B42="","",IF(OR(ISERROR(MATCH($B42,Community_Master!$A$2:$A$100,0)),$A42="",AND($H42<>"",$I42>$H42),AND($H42<>"",$J42>$H42),$I42<0,$J42<0,$K42<0,$P42<0,$Q42<0,$Y42<0,$Z42<0,$AA42<0,$AB42<0,$AC42<0),"ERROR","OK")) | AR42: =IF($B42="","",TRIM(IF(ISERROR(MATCH($B42,Community_Master!$A$2:$A$100,0)),"Invalid Community_ID; ","")&IF($A42="","Missing Report_Month; ","")&IF(AND($H42<>"",$I42>$H42),"Occupied_Units greater than Total_Units; ","")&IF(AND($H42<>"",$J42>$H42),"Leased_Units greater than Total_Units; ","")&IF($I42<0,"Occupied_Units negative; ","")&IF($J42<0,"Leased_Units negative; ","")&IF($P42<0,"Avg_Market_Rent negative; ","")))
... C501: =IFERROR(VLOOKUP($B501,Community_Master!$A$2:$K$100,2,FALSE),"") | D501: =IFERROR(VLOOKUP($B501,Community_Master!$A$2:$K$100,4,FALSE),"") | E501: =IFERROR(VLOOKUP($B501,Community_Master!$A$2:$K$100,5,FALSE),"") | F501: =IFERROR(VLOOKUP($B501,Community_Master!$A$2:$K$100,6,FALSE),"") | G501: =IFERROR(VLOOKUP($B501,Community_Master!$A$2:$K$100,8,FALSE),"") | H501: =IFERROR(VLOOKUP($B501,Community_Master!$A$2:$K$100,7,FALSE),"") | L501: =IF($H501="","",MAX($H501-$I501,0)) | M501: =IF($H501="","",IFERROR($I501/$H501,"")) | N501: =IF($H501="","",IFERROR($J501/$H501,"")) | T501: =IF($H501="","",IFERROR($H501*$P501,"")) | X501: =IF(OR($U501="",$W501=""),"",($U501+$V501)-$W501) | AQ501: =IF($B501="","",IF(OR(ISERROR(MATCH($B501,Community_Master!$A$2:$A$100,0)),$A501="",AND($H501<>"",$I501>$H501),AND($H501<>"",$J501>$H501),$I501<0,$J501<0,$K501<0,$P501<0,$Q501<0,$Y501<0,$Z501<0,$AA501<0,$AB501<0,$AC501<0),"ERROR","OK")) | AR501: =IF($B501="","",TRIM(IF(ISERROR(MATCH($B501,Community_Master!$A$2:$A$100,0)),"Invalid Community_ID; ","")&IF($A501="","Missing Report_Month; ","")&IF(AND($H501<>"",$I501>$H501),"Occupied_Units greater than Total_Units; ","")&IF(AND($H501<>"",$J501>$H501),"Leased_Units greater than Total_Units; ","")&IF($I501<0,"Occupied_Units negative; ","")&IF($J501<0,"Leased_Units negative; ","")&IF($P501<0,"Avg_Market_Rent negative; ","")))

Sheet Community_Master
A1: Community_ID | B1: Community_Name | C1: Short_Name | D1: Region | E1: Market | F1: Asset_Type | G1: Total_Units | H1: PMS_Property_Code | I1: Dashboard_Group | J1: Active_Flag | K1: Notes
A2: SER | B2: Sereno | C2: Sereno | D2: Florida | E2: Jacksonville | F2: Multifamily | G2: 320 | H2: SERENO | I2: Stabilized | J2: Yes | K2: Known total units from current ATLAS context.
A3: GKP | B3: Glen Kernan Park | C3: GKP | D3: Florida | E3: Jacksonville | F3: Senior | G3: 308 | H3: GKP | I3: Lease-Up | J3: Yes | K3: Also referred to as GKP.
A4: NOC | B4: Nocatee | C4: Nocatee | D4: Florida | E4: Jacksonville | F4: Senior | G4: 178 | H4: NOCATEE | I4: Lease-Up | J4: Yes | K4: Community included in dashboard lease-up tracking.
A5: FLO | B5: Florence Villa | C5: Florence Villa | D5: Florida | E5: Central Florida | F5: Multifamily | G5: 224 | H5: FLOVILLA | I5: Lease-Up | J5: Yes | K5: Community included in dashboard lease-up tracking.
A6: BAR | B6: Bartram | C6: Bartram | D6: Florida | E6: Jacksonville | F6: Multifamily | G6: 297 | H6: BARTRAM | I6: Stabilized | J6: Yes | K6: Community included in dashboard occupancy tracking.
A7: CIT | B7: Citrus Ridge | C7: Citrus Ridge | D7: Florida | E7: Central Florida | F7: Multifamily | G7: 222 | H7: CITRIDGE | I7: Lease-Up | J7: Yes | K7: Community included in dashboard lease-up tracking.
A8: VIE | B8: Viera | C8: Viera | D8: Florida | E8: Space Coast | F8: Senior | G8: 166 | H8: VIERA | I8: Lease-Up | J8: Yes | K8: Community included in dashboard lease-up tracking.
A9: BAY | B9: Baymeadows | C9: Baymeadows | D9: Florida | E9: Jacksonville | F9: Multifamily | G9: 340 | H9: BAYMEADOWS | I9: Lease-Up | J9: Yes | K9: Community included in dashboard lease-up tracking.
A10: DOR | B10: Doro | C10: Doro | D10: Florida | E10: Jacksonville | F10: Multifamily | G10: 247 | H10: DORO | I10: Stabilized | J10: Yes | K10: Known total units from portfolio context.
A11: STA | B11: St Augustine | C11: St Augustine | D11: Florida | E11: St. Augustine | F11: Lease-Up | G11: 272 | H11: STAUGUSTINE | I11: Lease-Up | J11: Yes | K11: Added for May 2026 St Augustine monthly upload mapping.

Sheet Data_Dictionary
A1: Field | B1: Required | C1: Type | D1: Allowed / Formula | E1: Agent Rule | F1: Power BI Role
A2: Report_Month | B2: Yes | C2: Date | D2: First day of reporting month | E2: Load or calculate per ATLAS monthly update rules | F2: Date key
A3: Community_ID | B3: Yes | C3: Text | D3: Use dropdown where available | E3: Load or calculate per ATLAS monthly update rules | F3: Dimension key
A4: Community_Name | B4: No | C4: Formula / Derived | D4: Do not manually overwrite unless correcting formula logic | E4: Map from Community_Master using Community_ID | F4: Attribute
A5: Region | B5: No | C5: Formula / Derived | D5: Do not manually overwrite unless correcting formula logic | E5: Map from Community_Master using Community_ID | F5: Attribute
A6: Market | B6: No | C6: Formula / Derived | D6: Do not manually overwrite unless correcting formula logic | E6: Map from Community_Master using Community_ID | F6: Attribute
A7: Asset_Type | B7: No | C7: Formula / Derived | D7: Do not manually overwrite unless correcting formula logic | E7: Map from Community_Master using Community_ID | F7: Attribute
A8: PMS_Property_Code | B8: No | C8: Formula / Derived | D8: Do not manually overwrite unless correcting formula logic | E8: Map from Community_Master using Community_ID | F8: Attribute
A9: Total_Units | B9: No | C9: Number | D9: >= 0 unless otherwise noted | E9: Map from Community_Master using Community_ID | F9: Measure
A10: Occupied_Units | B10: Yes | C10: Number | D10: >= 0 unless otherwise noted | E10: Load or calculate per ATLAS monthly update rules | F10: Measure
A11: Leased_Units | B11: Yes | C11: Number | D11: >= 0 unless otherwise noted | E11: Load or calculate per ATLAS monthly update rules | F11: Measure
A12: Preleased_Units | B12: No | C12: Number | D12: >= 0 unless otherwise noted | E12: Load or calculate per ATLAS monthly update rules | F12: Measure
... A45: Error_Detail | B45: No | C45: Formula / Derived | D45: Do not manually overwrite unless correcting formula logic | E45: Load or calculate per ATLAS monthly update rules | F45: Attribute

Sheet Validation_Lists
A1: Asset_Type | B1: Dashboard_Group | C1: Period_Status | D1: Source_System | E1: Row_Status | F1: Yes_No | G1: Upload_Type
A2: Lease-Up | B2: Lease-Up | C2: Actual | D2: Manual Upload | E2: OK | F2: Yes | G2: Monthly Close
A3: Multifamily | B3: Stabilized | C3: Budget | D3: Yardi | E3: ERROR | F3: No | G3: Weekly Flash
A4: Student | B4: Student | C4: Forecast | D4: Entrata | E4: REVIEW | G4: Reforecast
A5: Senior | B5: Senior | C5: Prior Month Restatement | D5: ResMan | G5: Correction
A6: Military | B6: Military | D6: RealPage
A7: Affordable | B7: Affordable | D7: AppFolio
A8: Mixed-Use | D8: Excel Export
D9: Other

Sheet Upload_Checks
A1: ATLAS Upload Checks
A3: Check | B3: Formula / Result | C3: Target | E3: Community Coverage | F3: Expected | G3: Rows Loaded | H3: Status
A4: Rows Loaded | B4: =COUNTA(Monthly_Upload!B2:B501) | C4: >= Active communities | E4: SER | F4: 1 | G4: =COUNTIF(Monthly_Upload!$B$2:$B$501,E4) | H4: =IF(G4>=F4,"OK","MISSING")
A5: Rows Marked ERROR | B5: =COUNTIF(Monthly_Upload!AQ2:AQ501,"ERROR") | C5: 0 | E5: GKP | F5: 1 | G5: =COUNTIF(Monthly_Upload!$B$2:$B$501,E5) | H5: =IF(G5>=F5,"OK","MISSING")
A6: Rows Marked OK | B6: =COUNTIF(Monthly_Upload!AQ2:AQ501,"OK") | C6: Match rows loaded | E6: NOC | F6: 1 | G6: =COUNTIF(Monthly_Upload!$B$2:$B$501,E6) | H6: =IF(G6>=F6,"OK","MISSING")
A7: Blank Community IDs | B7: =COUNTBLANK(Monthly_Upload!B2:B501) | C7: Ignore blanks below data | E7: FLO | F7: 1 | G7: =COUNTIF(Monthly_Upload!$B$2:$B$501,E7) | H7: =IF(G7>=F7,"OK","MISSING")
A8: Missing Report Month | B8: =COUNTIFS(Monthly_Upload!B2:B501,"<>",Monthly_Upload!A2:A501,"") | C8: 0 | E8: BAR | F8: 1 | G8: =COUNTIF(Monthly_Upload!$B$2:$B$501,E8) | H8: =IF(G8>=F8,"OK","MISSING")
A9: Occupied > Total Units | B9: =SUMPRODUCT(--(Monthly_Upload!H2:H501<>""),--(Monthly_Upload!I2:I501>Monthly_Upload!H2:H501),--(Monthly_Upload!B2:B501<>"")) | C9: 0 | E9: CIT | F9: 1 | G9: =COUNTIF(Monthly_Upload!$B$2:$B$501,E9) | H9: =IF(G9>=F9,"OK","MISSING")
A10: Leased > Total Units | B10: =SUMPRODUCT(--(Monthly_Upload!H2:H501<>""),--(Monthly_Upload!J2:J501>Monthly_Upload!H2:H501),--(Monthly_Upload!B2:B501<>"")) | C10: 0 | E10: VIE | F10: 1 | G10: =COUNTIF(Monthly_Upload!$B$2:$B$501,E10) | H10: =IF(G10>=F10,"OK","MISSING")
A11: Invalid Community IDs | B11: =SUMPRODUCT(--(Monthly_Upload!B2:B501<>""),--ISERROR(MATCH(Monthly_Upload!B2:B501,Community_Master!A2:A100,0))) | C11: 0 | E11: BAY | F11: 1 | G11: =COUNTIF(Monthly_Upload!$B$2:$B$501,E11) | H11: =IF(G11>=F11,"OK","MISSING")
A12: Overall Upload Status | B12: =IF(SUM(B5,B9:B11)=0,"READY TO LOAD","FIX ERRORS") | C12: READY TO LOAD | E12: DOR | F12: 1 | G12: =COUNTIF(Monthly_Upload!$B$2:$B$501,E12) | H12: =IF(G12>=F12,"OK","MISSING")
A13: Last Reviewed | B13: 2026-04-30 14:49

Sheet PowerBI_Schema
A1: Table | B1: Column | C1: Data Type | D1: Model Use | E1: Relationship / Notes
A2: Monthly_Upload | B2: Report_Month | C2: Date | D2: FactMonthlyPerformance | E2: Use as Date dimension relationship
A3: Monthly_Upload | B3: Community_ID | C3: Text | D3: FactMonthlyPerformance | E3: Many-to-one to Community_Master[Community_ID]
A4: Monthly_Upload | B4: Community_Name | C4: Text | D4: FactMonthlyPerformance
A5: Monthly_Upload | B5: Region | C5: Text | D5: FactMonthlyPerformance
A6: Monthly_Upload | B6: Market | C6: Text | D6: FactMonthlyPerformance
A7: Monthly_Upload | B7: Asset_Type | C7: Text | D7: FactMonthlyPerformance
A8: Monthly_Upload | B8: PMS_Property_Code | C8: Text | D8: FactMonthlyPerformance
A9: Monthly_Upload | B9: Total_Units | C9: Decimal Number | D9: FactMonthlyPerformance
A10: Monthly_Upload | B10: Occupied_Units | C10: Decimal Number | D10: FactMonthlyPerformance
A11: Monthly_Upload | B11: Leased_Units | C11: Decimal Number | D11: FactMonthlyPerformance
A12: Monthly_Upload | B12: Preleased_Units | C12: Decimal Number | D12: FactMonthlyPerformance
A13: Monthly_Upload | B13: Vacant_Units | C13: Decimal Number | D13: FactMonthlyPerformance
A14: Monthly_Upload | B14: Physical_Occupancy_% | C14: Decimal Number | D14: FactMonthlyPerformance
A15: Monthly_Upload | B15: Leased_% | C15: Decimal Number | D15: FactMonthlyPerformance
... A45: Monthly_Upload | B45: Error_Detail | C45: Text | D45: FactMonthlyPerformance
A46: Community_Master | B46: Community_ID | C46: Text | D46: DimensionCommunity | E46: One side of Community_ID relationship
A47: Community_Master | B47: Community_Name | C47: Text | D47: DimensionCommunity
A48: Community_Master | B48: Short_Name | C48: Text | D48: DimensionCommunity
A49: Community_Master | B49: Region | C49: Text | D49: DimensionCommunity
A50: Community_Master | B50: Market | C50: Text | D50: DimensionCommunity
A51: Community_Master | B51: Asset_Type | C51: Text | D51: DimensionCommunity
A52: Community_Master | B52: Total_Units | C52: Whole Number | D52: DimensionCommunity
A53: Community_Master | B53: PMS_Property_Code | C53: Text | D53: DimensionCommunity
A54: Community_Master | B54: Dashboard_Group | C54: Text | D54: DimensionCommunity
A55: Community_Master | B55: Active_Flag | C55: Text | D55: DimensionCommunity
A56: Community_Master | B56: Notes | C56: Text | D56: DimensionCommunity

Sheet Agent_Instructions
A1: Agent Ingestion Rules
A2: 1. Accept one Excel file only. The required upload tab is Monthly_Upload.
A3: 2. The grain must be one row per Report_Month + Community_ID. Do not create duplicate rows for the same month/community.
A4: 3. Community_ID is the mapping key. Match aliases to Community_Master before load. Examples: Glen Kernan Park = GKP, Sereno = SER.
A5: 4. Do not invent unit counts. Use Community_Master Total_Units when known. Flag missing Total_Units for review.
A6: 5. Standardize Report_Month to the first day of the month.
A7: 6. Convert occupancy percentages to decimal format, e.g., 95.6% = 0.956.
A8: 7. Preserve formulas in formula-driven columns. Paste source data only into editable input columns.
A9: 8. Run Upload_Checks. Return the file only when Overall Upload Status = READY TO LOAD.
A10: 9. If Row_Status = ERROR, preserve Error_Detail and do not load the row into production.
A11: 10. Save file as ATLAS_MonthlyUpload_YYYY-MM.xlsx.
A13: Editable columns for source data: A, B, I:K, O:S, U:W, Y:AP.
... A17: LOVE. SERVE. CARE. Powered by better insight, stronger service, and care for every community.
