Workbook

Sheet README
A1: ATLAS Monthly Portfolio Upload Template
A2: One standardized file to refresh the full monthly ATLAS dashboard across all communities.
A4: Workflow Step | B4: Action | D4: Recommended Tagline
A5: 1 | B5: Update Community_Master only when a community or mapping changes. | D5: LOVE. SERVE. CARE.
A6: 2 | B6: Paste one row per community per month into Monthly_Upload, including the five lead-source columns on that same row. | D6: Powered by better insight, stronger service, and care for every community.
A7: 3 | B7: Use dropdowns and Row_Status / Error_Detail to correct issues.
A8: 4 | B8: Review Upload_Checks before loading. | D8: Primary Keys | E8: Report_Month + Community_ID
A9: 5 | B9: Load Monthly_Upload into Power BI / ATLAS as the monthly fact table and use Floorplan_Occupancy for floor-plan occupancy detail. | D9: Community Mapping | E9: Community_ID joins every upload row to dashboard visuals.
A10: 6 | B10: Save as ATLAS_MonthlyUpload_YYYY-MM.xlsx. | D10: Power BI Grain | E10: One row per community per reporting month in Monthly_Upload; one row per floor plan in Floorplan_Occupancy.
D11: Do Not Rename | E11: Monthly_Upload, Community_Master, Data_Dictionary, Upload_Checks
D12: Agent Role | E12: Clean, map, validate, and return this schema with lead-source detail on Monthly_Upload.

Sheet Monthly_Upload
A1: Report_Month | B1: Community_ID | C1: Community_Name | D1: Region | E1: Market | F1: Asset_Type | G1: PMS_Property_Code | H1: Total_Units | I1: Occupied_Units | J1: Leased_Units | K1: Preleased_Units | L1: Vacant_Units | M1: Physical_Occupancy_% | N1: Leased_% | O1: Economic_Occupancy_% | P1: Avg_Market_Rent | Q1: Actual_Rent | R1: Concessions_$ | S1: Delinquency_$ | T1: Gross_Potential_Rent_$ | U1: Collected_Rent_$ | V1: Other_Income_$ | W1: Operating_Expenses_$ | X1: NOI_$ | Y1: Traffic | Z1: Leads | AA1: Lead_Walk_Ins | AB1: Lead_Off_Site_Event | AC1: Lead_Calls | AD1: Lead_Emails_Online | AE1: Lead_Chat_Text_Other | AF1: Tours | AG1: Applications | AH1: Approved_Applications | AI1: Move_Ins | AJ1: Move_Outs | AK1: Renewals_Sent | AL1: Renewals_Signed | AM1: Reviews_Count | AN1: Avg_Review_Rating | AO1: Open_Work_Orders | AP1: Completed_Work_Orders | AQ1: Period_Status | AR1: Source_System | AS1: Source_File_Name | AT1: Agent_Notes | AU1: Last_Updated | AV1: Row_Status | AW1: Error_Detail

Sheet Community_Master
A1: Community_ID | B1: Community_Name | C1: Short_Name | D1: Region | E1: Market | F1: Asset_Type | G1: Total_Units | H1: PMS_Property_Code | I1: Dashboard_Group | J1: Active_Flag | K1: Notes
A2: SER | B2: Sereno | C2: Sereno | D2: Florida | E2: Jacksonville | F2: Multifamily | G2: 320 | H2: SERENO | I2: Stabilized | J2: Yes | K2: Known total units from current ATLAS context.
A3: GKP | B3: Glen Kernan Park | C3: GKP | D3: Florida | E3: Jacksonville | F3: Senior | G3: 308 | H3: GKP | I3: Lease-Up | J3: Yes | K3: Also referred to as GKP.
A4: NOC | B4: Nocatee | C4: Nocatee | D4: Florida | E4: Jacksonville | F4: Senior | G4: 178 | H4: NOCATEE | I4: Lease-Up | J4: Yes | K4: Community included in dashboard lease-up tracking.
A5: FLO | B5: Florence Villa | C5: Florence Villa | D5: Florida | E5: Central Florida | F5: Multifamily | G5: 224 | H5: FLOVILLA | I5: Lease-Up | J5: Yes | K5: Community included in dashboard lease-up tracking.
A6: BAR | B6: Bartram | C6: Bartram | D6: Florida | E6: Jacksonville | F6: Multifamily | G6: 297 | H6: BARTRAM | I6: Stabilized | J6: Yes | K6: Community included in dashboard occupancy tracking.
A7: CIT | B7: Citrus Ridge | C7: Citrus Ridge | D7: Florida | E7: Central Florida | F7: Multifamily | G7: 222 | H7: CITRIDGE | I7: Lease-Up | J7: Yes | K7: Community included in dashboard lease-up tracking.
A8: VIE | B8: Viera | C8: Viera | D8: Florida | E8: Space Coast | F8: Senior | G8: 166 | H8: VIERA | I8: Lease-Up | J8: Yes | K8: Community included in dashboard lease-up tracking.
A9: BAY | B9: Baymeadows | C9: Baymeadows | D9: Florida | E9: Jacksonville | F9: Multifamily | G9: 340 | H9: BAYMEADOWS | I9: Lease-Up | J9: Yes | K9: Community included in dashboard lease-up tracking.
A10: DOR | B10: Doro | C10: Doro | D10: Florida | E10: Jacksonville | F10: Multifamily | G10: 247 | H10: DORO | I10: Stabilized | J10: Yes | K10: Known total units from portfolio context.

Sheet Data_Dictionary
A1: Field | B1: Required | C1: Type | D1: Allowed / Formula | E1: Agent Rule | F1: Power BI Role
A2: Report_Month | B2: Yes | C2: Date | D2: First day of reporting month | E2: Load or calculate per ATLAS monthly update rules | F2: Date key
A3: Community_ID | B3: Yes | C3: Text | D3: Use dropdown where available | E3: Load or calculate per ATLAS monthly update rules | F3: Dimension key
A4: Community_Name | B4: No | C4: Formula / Derived | D4: Do not manually overwrite unless correcting formula logic | E4: Map from Community_Master using Community_ID | F4: Attribute
A5: Region | B5: No | C5: Formula / Derived | D5: Do not manually overwrite unless correcting formula logic | E5: Map from Community_Master using Community_ID | F5: Attribute
A6: Market | B6: No | C6: Formula / Derived | D6: Do not manually overwrite unless correcting formula logic | E6: Map from Community_Master using Community_ID | F6: Attribute
A7: Asset_Type | B7: No | C7: Formula / Derived | D7: Do not manually overwrite unless correcting formula logic | E7: Map from Community_Master using Community_ID | F7: Attribute
A8: PMS_Property_Code | B8: No | C8: Formula / Derived | D8: Do not manually overwrite unless correcting formula logic | E8: Map from Community_Master using Community_ID | F8: Attribute
A9: Total_Units | B9: No | C9: Number | D9: >= 0 unless otherwise noted | E9: Map from Community_Master using Community_ID | F9: Measure
A10: Occupied_Units | B10: Yes | C10: Number | D10: >= 0 unless otherwise noted | E10: Load or calculate per ATLAS monthly update rules | F10: Measure
A11: Leased_Units | B11: Yes | C11: Number | D11: >= 0 unless otherwise noted | E11: Load or calculate per ATLAS monthly update rules | F11: Measure
A12: Preleased_Units | B12: No | C12: Number | D12: >= 0 unless otherwise noted | E12: Load or calculate per ATLAS monthly update rules | F12: Measure
... A506: Lead_Chat_Text_Other | B506: Yes | C506: Number | D506: >= 0 unless otherwise noted | E506: Load from chat + text + other lead-source detail on the same Monthly_Upload row | F506: Measure

Sheet Validation_Lists
A1: Asset_Type | B1: Dashboard_Group | C1: Period_Status | D1: Source_System | E1: Row_Status | F1: Yes_No | G1: Upload_Type
A2: Lease-Up | B2: Lease-Up | C2: Actual | D2: Manual Upload | E2: OK | F2: Yes | G2: Monthly Close
A3: Multifamily | B3: Stabilized | C3: Budget | D3: Yardi | E3: ERROR | F3: No | G3: Weekly Flash
A4: Student | B4: Student | C4: Forecast | D4: Entrata | E4: REVIEW | G4: Reforecast
A5: Senior | B5: Senior | C5: Prior Month Restatement | D5: ResMan | G5: Correction
A6: Military | B6: Military | D6: RealPage
A7: Affordable | B7: Affordable | D7: AppFolio
A8: Mixed-Use | D8: Excel Export
D9: Other

Sheet Upload_Checks
A1: ATLAS Upload Checks
A3: Check | B3: Formula / Result | C3: Target | E3: Community Coverage | F3: Expected | G3: Rows Loaded | H3: Status
A4: Rows Loaded | B4: =COUNTA(Monthly_Upload!B2:B501) | C4: >= Active communities | E4: SER | F4: 1 | G4: =COUNTIF(Monthly_Upload!$B$2:$B$501,E4) | H4: =IF(G4>=F4,"OK","MISSING")
A5: Rows Marked ERROR | B5: =COUNTIF(Monthly_Upload!AQ2:AQ501,"ERROR") | C5: 0 | E5: GKP | F5: 1 | G5: =COUNTIF(Monthly_Upload!$B$2:$B$501,E5) | H5: =IF(G5>=F5,"OK","MISSING")
A6: Rows Marked OK | B6: =COUNTIF(Monthly_Upload!AQ2:AQ501,"OK") | C6: Match rows loaded | E6: NOC | F6: 1 | G6: =COUNTIF(Monthly_Upload!$B$2:$B$501,E6) | H6: =IF(G6>=F6,"OK","MISSING")
A7: Blank Community IDs | B7: =COUNTBLANK(Monthly_Upload!B2:B501) | C7: Ignore blanks below data | E7: FLO | F7: 1 | G7: =COUNTIF(Monthly_Upload!$B$2:$B$501,E7) | H7: =IF(G7>=F7,"OK","MISSING")
A8: Missing Report Month | B8: =COUNTIFS(Monthly_Upload!B2:B501,"<>",Monthly_Upload!A2:A501,"") | C8: 0 | E8: BAR | F8: 1 | G8: =COUNTIF(Monthly_Upload!$B$2:$B$501,E8) | H8: =IF(G8>=F8,"OK","MISSING")
A9: Occupied > Total Units | B9: =SUMPRODUCT(--(Monthly_Upload!H2:H501<>""),--(Monthly_Upload!I2:I501>Monthly_Upload!H2:H501),--(Monthly_Upload!B2:B501<>"")) | C9: 0 | E9: CIT | F9: 1 | G9: =COUNTIF(Monthly_Upload!$B$2:$B$501,E9) | H9: =IF(G9>=F9,"OK","MISSING")
A10: Leased > Total Units | B10: =SUMPRODUCT(--(Monthly_Upload!H2:H501<>""),--(Monthly_Upload!J2:J501>Monthly_Upload!H2:H501),--(Monthly_Upload!B2:B501<>"")) | C10: 0 | E10: VIE | F10: 1 | G10: =COUNTIF(Monthly_Upload!$B$2:$B$501,E10) | H10: =IF(G10>=F10,"OK","MISSING")
A11: Invalid Community IDs | B11: =SUMPRODUCT(--(Monthly_Upload!B2:B501<>""),--ISERROR(MATCH(Monthly_Upload!B2:B501,Community_Master!A2:A100,0))) | C11: 0 | E11: BAY | F11: 1 | G11: =COUNTIF(Monthly_Upload!$B$2:$B$501,E11) | H11: =IF(G11>=F11,"OK","MISSING")
A12: Overall Upload Status | B12: =IF(SUM(B5,B9:B11)=0,"READY TO LOAD","FIX ERRORS") | C12: READY TO LOAD | E12: DOR | F12: 1 | G12: =COUNTIF(Monthly_Upload!$B$2:$B$501,E12) | H12: =IF(G12>=F12,"OK","MISSING")
A13: Last Reviewed | B13: 2026-04-30 14:49

Sheet PowerBI_Schema
A1: Table | B1: Column | C1: Data Type | D1: Model Use | E1: Relationship / Notes
A2: Monthly_Upload | B2: Report_Month | C2: Date | D2: FactMonthlyPerformance | E2: Use as Date dimension relationship
A3: Monthly_Upload | B3: Community_ID | C3: Text | D3: FactMonthlyPerformance | E3: Many-to-one to Community_Master[Community_ID]
A4: Monthly_Upload | B4: Community_Name | C4: Text | D4: FactMonthlyPerformance
A5: Monthly_Upload | B5: Region | C5: Text | D5: FactMonthlyPerformance
A6: Monthly_Upload | B6: Market | C6: Text | D6: FactMonthlyPerformance
A7: Monthly_Upload | B7: Asset_Type | C7: Text | D7: FactMonthlyPerformance
A8: Monthly_Upload | B8: PMS_Property_Code | C8: Text | D8: FactMonthlyPerformance
A9: Monthly_Upload | B9: Total_Units | C9: Decimal Number | D9: FactMonthlyPerformance
A10: Monthly_Upload | B10: Occupied_Units | C10: Decimal Number | D10: FactMonthlyPerformance
A11: Monthly_Upload | B11: Leased_Units | C11: Decimal Number | D11: FactMonthlyPerformance
A12: Monthly_Upload | B12: Preleased_Units | C12: Decimal Number | D12: FactMonthlyPerformance
A13: Monthly_Upload | B13: Vacant_Units | C13: Decimal Number | D13: FactMonthlyPerformance
A14: Monthly_Upload | B14: Physical_Occupancy_% | C14: Decimal Number | D14: FactMonthlyPerformance
A15: Monthly_Upload | B15: Leased_% | C15: Decimal Number | D15: FactMonthlyPerformance
... A45: Monthly_Upload | B45: Error_Detail | C45: Text | D45: FactMonthlyPerformance
A46: Community_Master | B46: Community_ID | C46: Text | D46: DimensionCommunity | E46: One side of Community_ID relationship
A47: Community_Master | B47: Community_Name | C47: Text | D47: DimensionCommunity
A48: Community_Master | B48: Short_Name | C48: Text | D48: DimensionCommunity
A49: Community_Master | B49: Region | C49: Text | D49: DimensionCommunity
A50: Community_Master | B50: Market | C50: Text | D50: DimensionCommunity
A51: Community_Master | B51: Asset_Type | C51: Text | D51: DimensionCommunity
A52: Community_Master | B52: Total_Units | C52: Whole Number | D52: DimensionCommunity
A53: Community_Master | B53: PMS_Property_Code | C53: Text | D53: DimensionCommunity
A54: Community_Master | B54: Dashboard_Group | C54: Text | D54: DimensionCommunity
A55: Community_Master | B55: Active_Flag | C55: Text | D55: DimensionCommunity
A56: Community_Master | B56: Notes | C56: Text | D56: DimensionCommunity
A502: Monthly_Upload | B502: Lead_Walk_Ins | C502: Decimal Number | D502: FactMonthlyPerformance | E502: Lead-source detail must be on the Monthly_Upload row.
A503: Monthly_Upload | B503: Lead_Off_Site_Event | C503: Decimal Number | D503: FactMonthlyPerformance | E503: Lead-source detail must be on the Monthly_Upload row.
A504: Monthly_Upload | B504: Lead_Calls | C504: Decimal Number | D504: FactMonthlyPerformance | E504: Lead-source detail must be on the Monthly_Upload row.
A505: Monthly_Upload | B505: Lead_Emails_Online | C505: Decimal Number | D505: FactMonthlyPerformance | E505: Lead-source detail must be on the Monthly_Upload row.
A506: Monthly_Upload | B506: Lead_Chat_Text_Other | C506: Decimal Number | D506: FactMonthlyPerformance | E506: Lead-source detail must be on the Monthly_Upload row.
A507: Floorplan_Occupancy | B507: Community_ID | C507: Text | D507: FactFloorplanOccupancy | E507: Many-to-one to Community_Master[Community_ID].
A508: Floorplan_Occupancy | B508: Floor_Plan_Name | C508: Text | D508: FactFloorplanOccupancy | E508: Use source floor-plan name or code when no alias exists.
A509: Floorplan_Occupancy | B509: Floor_Plan_Code | C509: Text | D509: FactFloorplanOccupancy | E509: Raw box score floor-plan code.
A510: Floorplan_Occupancy | B510: Occupied_Units | C510: Decimal Number | D510: FactFloorplanOccupancy | E510: Floor-plan occupied unit count from the Availability row.
A511: Floorplan_Occupancy | B511: Physical_Occupancy_% | C511: Decimal Number | D511: FactFloorplanOccupancy | E511: Floor-plan occupancy rate from the Availability row.

Sheet Agent_Instructions
A1: Agent Ingestion Rules
A2: 1. Accept one Excel file only. The required upload tab is Monthly_Upload.
A3: 2. The grain must be one row per Report_Month + Community_ID. Do not create duplicate rows for the same month/community.
A4: 3. Community_ID is the mapping key. Match aliases to Community_Master before load. Examples: Glen Kernan Park = GKP, Sereno = SER.
A5: 4. Do not invent unit counts. Use Community_Master Total_Units when known. Flag missing Total_Units for review.
A6: 5. Standardize Report_Month to the first day of the month.
A7: 6. Convert occupancy percentages to decimal format, e.g., 95.6% = 0.956.
A8: 7. Preserve formulas in formula-driven columns. Paste source data only into editable input columns.
A9: 8. Run Upload_Checks. Return the file only when Overall Upload Status = READY TO LOAD.
A10: 9. If Row_Status = ERROR, preserve Error_Detail and do not load the row into production.
A11: 10. Save file as ATLAS_MonthlyUpload_YYYY-MM.xlsx.
A13: Editable columns for source data: A, B, I:K, O:S, U:W, Y:AP.
... A17: LOVE. SERVE. CARE. Powered by better insight, stronger service, and care for every community.

Sheet Floorplan_Occupancy
A1: Report_Month | B1: Community_ID | C1: Community_Name | D1: Floor_Plan_Name | E1: Floor_Plan_Code | F1: Avg_SQFT | G1: Total_Units | H1: Occupied_Units | I1: Available_Units | J1: Leased_Units | K1: Physical_Occupancy_% | L1: Leased_% | M1: Avg_Market_Rent | N1: Actual_Rent | O1: Source_System | P1: Source_File_Name | Q1: Agent_Notes
